MANIFEST.in
README.rst
requirements.txt
setup.py
slacker_cli/__init__.py
slacker_cli.egg-info/PKG-INFO
slacker_cli.egg-info/SOURCES.txt
slacker_cli.egg-info/dependency_links.txt
slacker_cli.egg-info/entry_points.txt
slacker_cli.egg-info/requires.txt
slacker_cli.egg-info/top_level.txt