Metadata-Version: 1.1
Name: slacker-cli
Version: 0.3.0
Summary: Send messages to slack from command line
Home-page: https://github.com/juanpabloaj/slacker-cli
Author: JuanPablo AJ
Author-email: jpabloaj@gmail.com
License: MIT
Platform: UNKNOWN
Classifier: Programming Language :: Python
Classifier: Programming Language :: Python :: 2.6
Classifier: Programming Language :: Python :: 2.7
Classifier: Programming Language :: Python :: 3.3
Classifier: Programming Language :: Python :: 3.4
